PROJECT/battleship.v
module battleship (
  input            clk,
  input            rst,
  input            start,
  input      [1:0] X,
  input      [1:0] Y,
  input            pAb,
  input            pBb,
  output reg [7:0] disp0,
  output reg [7:0] disp1,
  output reg [7:0] disp2,
  output reg [7:0] disp3,
  output reg [7:0] led
);

parameter IDLE = 4'd0, SHOW_A = 4'd1, A_IN = 4'd2, ERROR_A = 4'd3, SHOW_B = 4'd4;
parameter B_IN = 4'd5, ERROR_B = 4'd6, SHOW_SCORE = 4'd7, A_SHOOT = 4'd8, A_SINK = 4'd9;
parameter A_WIN = 4'd10, B_SHOOT = 4'd11, B_SINK = 4'd12, B_WIN = 4'd13;

reg [3:0] state, next_state;
reg [3:0] mapA [15:0];
reg [3:0] mapB [15:0];
reg [2:0] score_A=0, score_B=0;
reg [15:0] timer, timer_winner;
reg [1:0] input_count_A, input_count_B;
reg [3:0] index;

// Combinational block for SSDs and LEDs
always @(*) begin
  // Default values
  disp0 = 8'b00000000;
  disp1 = 8'b00000000;
  disp2 = 8'b00000000;
  disp3 = 8'b00000000;
  led = 8'b00000000;

  case (state)
    IDLE: begin
      disp3 = 8'b00000110;  // 'I'
      disp2 = 8'b00111111;  // 'd'
      disp1 = 8'b00111000;  // 'l'
      disp0 = 8'b01111001;  // 'E'
      led = 8'b10011001;
    end
    SHOW_A: begin
      disp3 = 8'b01110111;  // 'A'
    end
    A_IN: begin
      led <= 8'b10000000; //LED 7 blink
      led[7:6] <= input_count_A;

      // Display X coordinate
      case (X)
        2'b00: disp1 = 8'b00111111; // 0
        2'b01: disp1 = 8'b00000110; // 1
        2'b10: disp1 = 8'b01011011; // 2
        2'b11: disp1 = 8'b01001111; // 3
        default: disp1 = 8'b11111111; // Undefined
      endcase

      // Display Y coordinate
      case (Y)
        2'b00: disp0 = 8'b00111111; // 0
        2'b01: disp0 = 8'b00000110; // 1
        2'b10: disp0 = 8'b01011011; // 2
        2'b11: disp0 = 8'b01001111; // 3
        default: disp0 = 8'b11111111; // Undefined
      endcase
    end
    ERROR_A: begin
      disp3 = 8'b01111001;  // 'E'
      disp2 = 8'b00110001;  // 'r'
      disp1 = 8'b00110001;  // 'r'
      disp0 = 8'b0011111;  // 'o'
      led = 8'b10011001;
    end
    SHOW_B: begin
      disp3 = 8'b01111111;  // 'B'
    end
    B_IN: begin
      led <= 8'b10000000; //All leds off
      led <= input_count_B;

      // Display X coordinate
      case (X)
        2'b00: disp1 = 8'b00111111; // 0
        2'b01: disp1 = 8'b00000110; // 1
        2'b10: disp1 = 8'b01011011; // 2
        2'b11: disp1 = 8'b01001111; // 3
        default: disp1 = 8'b11111111; // Undefined
      endcase

      // Display Y coordinate
      case (Y)
        2'b00: disp0 = 8'b00111111; // 0
        2'b01: disp0 = 8'b00000110; // 1
        2'b10: disp0 = 8'b01011011; // 2
        2'b11: disp0 = 8'b01001111; // 3
        default: disp0 = 8'b11111111; // Undefined
      endcase
    end
    ERROR_B: begin
      disp3 = 8'b01111001;  // 'E'
      disp2 = 8'b00110001;  // 'r'
      disp1 = 8'b00110001;  // 'r'
      disp0 = 8'b00111111;   // 'o'
      led = 8'b10011001;
    end
    SHOW_SCORE: begin
      case (timer_winner)
        2'b00: disp2 = 8'b00111111; // 0
        2'b01: disp2 = 8'b00000110; // 1
        2'b10: disp2 = 8'b01011011; // 2
        2'b11: disp2 = 8'b01001111; // 3
        default: disp2 = 8'b11111111; // Undefined
      endcase
      disp1 = 8'b01000000;  // '-'
      case (timer_winner)
        2'b00: disp0 = 8'b00111111;
        2'b01: disp0 = 8'b00000110; // 1
        2'b10: disp0 = 8'b01011011; // 2
        2'b11: disp0 = 8'b01001111; // 3
        default: disp0 = 8'b11111111; // Undefined
      endcase
      led = 8'b10010101;
      // Score for B
    end
    A_SHOOT:begin
      led <= 8'b10011001;
      led[5:4] <= score_A[1:0];  //score A blink
      led[3:2] <= score_B[1:0];  //score B blink
      case (X)
        2'b00: disp1 = 8'b00111111; // 0
        2'b01: disp1 = 8'b00000110; // 1
        2'b10: disp1 = 8'b01011011; // 2
        2'b11: disp1 = 8'b01001111; // 3
        default: disp1 = 8'b11111111; // Undefined
      endcase

      // Display Y coordinate
      case (Y)
        2'b00: disp0 = 8'b00111111; // 0
        2'b01: disp0 = 8'b00000110; // 1
        2'b10: disp0 = 8'b01011011; // 2
        2'b11: disp0 = 8'b01001111; // 3
        default: disp0 = 8'b11111111; // Undefined
      endcase
      
    end
    A_SINK:begin
      led = 8'b10011001;
   
      case (score_A)
      3'b000: disp2 = 8'b00111111; // 0
      3'b001: disp2 = 8'b00000110; // 1
      3'b010: disp2 = 8'b01011011; // 2
      3'b011: disp2 = 8'b01001111; // 3
      3'b100: disp2 = 8'b01100110; // 4
      default: disp2 = 8'b11111111; // Undefined
    endcase
    disp1 = 8'b01000000;  // '-'
    case (score_B)
    3'b000: disp0 = 8'b00111111; // 0
    3'b001: disp0 = 8'b00000110; // 1
    3'b010: disp0 = 8'b01011011; // 2
    3'b011: disp0 = 8'b01001111; // 3
    3'b100: disp0 = 8'b01100110; // 4
      default: disp0 = 8'b11111111; // Undefined
    endcase
  end

   
    
    B_SINK:begin
      disp3= 8'b00000000;
      case (score_A)
      3'b000: disp2 = 8'b00111111; // 0
      3'b001: disp2 = 8'b00000110; // 1
      3'b010: disp2 = 8'b01011011; // 2
      3'b011: disp2 = 8'b01001111; // 3
      3'b100: disp2 = 8'b01100110; // 4
      default: disp2 = 8'b11111111; // Undefined
    endcase
    disp1 = 8'b01000000;  // '-'
    case (score_B)
    3'b000: disp0 = 8'b00111111; // 0
    3'b001: disp0 = 8'b00000110; // 1
    3'b010: disp0 = 8'b01011011; // 2
    3'b011: disp0 = 8'b01001111; // 3
    3'b100: disp0 = 8'b01100110; // 4
      default: disp0 = 8'b11111111; // Undefined
    endcase
    end
    B_SHOOT:begin
      led <= 8'b00000000;
      led[5:4] <= score_A[1:0];  //score A blink
      led[3:2] <= score_B[1:0];  //score B blink
     
      case (X)
        2'b00: disp1 = 8'b00111111; // 0
        2'b01: disp1 = 8'b00000110; // 1
        2'b10: disp1 = 8'b01011011; // 2
        2'b11: disp1 = 8'b01001111; // 3
        default: disp1 = 8'b11111111; // Undefined
      endcase

      // Display Y coordinate
      case (Y)
        2'b00: disp0 = 8'b00111111; // 0
        2'b01: disp0 = 8'b00000110; // 1
        2'b10: disp0 = 8'b01011011; // 2
        2'b11: disp0 = 8'b01001111; // 3
        default: disp0 = 8'b11111111; // Undefined
      endcase
      
    end
    A_WIN: begin

    disp3 = 8'b01110111;  // 'A'

    case (score_A)
      3'b000: disp2 = 8'b00111111; // 0
      3'b001: disp2 = 8'b00000110; // 1
      3'b010: disp2 = 8'b01011011; // 2
      3'b011: disp2 = 8'b01001111; // 3
      3'b100: disp2 = 8'b01100110; // 4
      default: disp2 = 8'b11111111; // Undefined
    endcase
    disp1 = 8'b01000000;  // '-'
    case (score_B)
    3'b000: disp0 = 8'b00111111; // 0
    3'b001: disp0 = 8'b00000110; // 1
    3'b010: disp0 = 8'b01011011; // 2
    3'b011: disp0 = 8'b01001111; // 3
    3'b100: disp0 = 8'b01100110; // 4
      default: disp0 = 8'b11111111; // Undefined
    endcase
    led = 8'b11111111;  // LED dance

    end
    B_WIN: begin
    disp3 = 8'b01111111;  // 'B'

    // Display Player A's score on disp2
    case (score_A)
      3'b000: disp2 = 8'b00111111; // 0
      3'b001: disp2 = 8'b00000110; // 1
      3'b010: disp2 = 8'b01011011; // 2
      3'b011: disp2 = 8'b01001111; // 3
      3'b100: disp2 = 8'b01100110; // 4
      default: disp2 = 8'b11111111; // Undefined
    endcase

    disp1 = 8'b01000000;  // '-'

    // Display Player B's score on disp0
    case (score_B)
      3'b000: disp0 = 8'b00111111; // 0
      3'b001: disp0 = 8'b00000110; // 1
      3'b010: disp0 = 8'b01011011; // 2
      3'b011: disp0 = 8'b01001111; // 3
      3'b100: disp0 = 8'b01100110; // 4
      default: disp0 = 8'b11111111; // Undefined
    endcase

    led = 8'b11111111;  // LED dance
end

  
  endcase
end


// Sequential block for state and game logic
always @(posedge clk or posedge rst) begin
  if (rst) begin
    state <= IDLE;
    next_state <= IDLE;
    score_A <= 0;
    score_B <= 0;
    input_count_A <= 0;
    input_count_B <= 0;
    timer <= 0;
    timer_winner<= 0;
    

    mapA[0] <= 0; mapA[1] <= 0; mapA[2] <= 0; mapA[3] <= 0;
    mapA[4] <= 0; mapA[5] <= 0; mapA[6] <= 0; mapA[7] <= 0;
    mapA[8] <= 0; mapA[9] <= 0; mapA[10] <= 0; mapA[11] <= 0;
    mapA[12] <= 0; mapA[13] <= 0; mapA[14] <= 0; mapA[15] <= 0;

    mapB[0] <= 0; mapB[1] <= 0; mapB[2] <= 0; mapB[3] <= 0;
    mapB[4] <= 0; mapB[5] <= 0; mapB[6] <= 0; mapB[7] <= 0;
    mapB[8] <= 0; mapB[9] <= 0; mapB[10] <= 0; mapB[11] <= 0;
    mapB[12] <= 0; mapB[13] <= 0; mapB[14] <= 0; mapB[15] <= 0;
  end else begin
    state <= next_state;
    index <= Y * 4 + X;

    case (state)
    IDLE: if (start) begin
      timer <= 0;
      next_state <= SHOW_A;
    end         
    SHOW_A: if (timer == 50) begin // Adjusted for longer display duration
      next_state <= A_IN ;
      timer <= 0;
    end else begin
      timer <= timer + 1;
    end 
    A_IN: begin
      timer <= 0;
      if (pAb && mapA[index] == 0) begin
        mapA[index] <= 1;
        if (input_count_A == 3) 
          next_state <= SHOW_B;
        else 
          input_count_A <= input_count_A + 1;
      end else if (pAb && mapA[index] == 1) 
        //next_state <= ERROR_A;
        next_state <= A_IN;
    end
    ERROR_A: if (timer == 100) begin // Increased duration for error visibility
      next_state <= A_IN;
      timer <= 0;
    end else begin
      timer <= timer + 1;
    end
    SHOW_B: if (timer == 100) begin // Adjusted for longer display duration
      next_state <= B_IN ;
      timer <= 0;
    end else begin
      timer <= timer + 1;
    end 
    B_IN: begin
      timer <= 0;
      if (pBb) begin
        if (mapB[index] == 0) begin
          mapB[index] <= 1;
          if (input_count_B < 3) begin
            input_count_B <= input_count_B + 1;
            next_state <= B_IN;
          end else begin
            input_count_B <= input_count_B + 1; // Final input for Player B
            next_state <= SHOW_SCORE;
          end
        end else begin
          //next_state <= ERROR_B;
          next_state <= B_IN;
        end
      end
    end
    ERROR_B: if (timer == 100) begin // Increased duration for error visibility
      next_state <= B_IN;
      timer <= 0;
    end else begin
      timer <= timer + 1;
    end
    SHOW_SCORE: if (timer == 200) next_state <= A_SHOOT; else timer <= timer + 1;
    A_SHOOT: if (pAb) begin
      timer <= 0;
      if (mapB[index]) begin
        score_A <= score_A + 1;
        mapB[index] <= 0;
        next_state <= A_SINK;
      end else 
        next_state <= A_SINK;
    end
    A_SINK: if (timer == 100) begin // Adjusted sink display time
      timer_winner <= timer_winner + 1;
      timer <= 0;
      if (score_A >= 4) 
        next_state <= A_WIN;
      else 
        next_state <= B_SHOOT;
    end else timer <= timer + 1;
    B_SHOOT: if (pBb) begin
      if (mapA[index]) begin
        score_B <= score_B + 1;
        mapA[index] <= 0;
        next_state <= B_SINK;
      end else 
        next_state <= B_SINK;
    end
    B_SINK: if (timer == 100) begin 
      timer=0;
      timer_winner=0;// Adjusted sink display time
      if (score_B >=4) 
        next_state <= B_WIN;
      else 
        next_state <= A_SHOOT;
    end else timer <= timer + 1;

      A_WIN: begin
      
          // Kazanma durumu tamamlandı, tüm oyun değişkenlerini sıfırla
          next_state <= state; // IDLE durumuna geçiş yap
         
      
        
        
      end
      
      B_WIN: begin
    
          // Kazanma durumu tamamlandı, tüm oyun değişkenlerini sıfırla
          next_state <= state; // IDLE durumuna geçiş yap
          
      
 
       
      end
      
    endcase
  end
end

endmodule

PROJECT/battleship_tb.v
module battleship_tb();

  reg clk;
  reg rst;
  reg start;
  reg [1:0] X;
  reg [1:0] Y;
  reg pAb;
  reg pBb;
  wire [7:0] disp0;
  wire [7:0] disp1;
  wire [7:0] disp2;
  wire [7:0] disp3;
  wire [7:0] led;

  battleship  ba00 (
    .clk(clk),
    .rst(rst),
    .start(start),
    .X(X),
    .Y(Y),
    .pAb(pAb),
    .pBb(pBb),
    .disp0(disp0),
    .disp1(disp1),
    .disp2(disp2),
    .disp3(disp3),
    .led(led)
  );
  
  parameter HP = 5;
  parameter FP = (20*HP);

  always #HP  clk = ~clk ;

  initial begin
      $dumpfile("battleship_tb.vcd"); 
      $dumpvars(0,battleship_tb);

      $display("Simulation started.");
      clk = 1;
      rst = 1;
      start = 0;
      X = 0;
      Y = 0;
      pAb = 0;
      pBb = 0;
      #FP;
      rst = 0;
      #FP;
      start = 1;
      #(5*FP);
      start = 0;
      #FP;

      //Player A placing
      pAb = 1; X = 0; Y = 0; #FP; pAb = 0; #FP;
      pAb = 1; X = 0; Y = 1; #FP; pAb = 0; #FP;
      pAb = 1; X = 1; Y = 0; #FP; pAb = 0; #FP;
      pAb = 1; X = 1; Y = 1; #FP; pAb = 0; #FP;

      //Player B placing
      pBb = 1; X = 0; Y = 0; #FP; pBb = 0; #FP;
      pBb = 1; X = 0; Y = 1; #FP; pBb = 0; #FP;
      pBb = 1; X = 1; Y = 0; #FP; pBb = 0; #FP;
      pBb = 1; X = 1; Y = 1; #FP; pBb = 0; #FP;

      //Player A and B shoot
      pAb = 1; X = 0; Y = 0; #FP; pAb = 0; #FP;
      pBb = 1; X = 0; Y = 0; #FP; pBb = 0; #FP;

      pAb = 1; X = 0; Y = 1; #FP; pAb = 0; #FP;
      pBb = 1; X = 1; Y = 0; #FP; pBb = 0; #FP;

      pAb = 1; X = 1; Y = 1; #FP; pAb = 0; #FP;
      pBb = 1; X = 1; Y = 1; #FP; pBb = 0; #FP;

      pAb = 1; X = 1; Y = 1; #FP; pAb = 0; #FP;
      pBb = 1; X = 0; Y = 1; #FP; pBb = 0; #FP;


      $display("Simulation finished.");
      $finish(); // Finish simulation.
  end

  // Dinamik bitirme için kazanan kontrolü
  always @(posedge clk) begin
      if (ba00.state == 10 || ba00.state == 13) begin
          $display("Game Over! Winner detected at time %0t. State = %0d", $time, ba00.state);
          $finish;
      end
  end

  // Durum takibi
  always @(posedge clk) begin
      $display("Time: %0t, State: %0d, Next State: %0d, Score A: %0d, Score B: %0d", 
               $time, ba00.state, ba00.next_state, ba00.score_A, ba00.score_B);
  end

endmodule

PROJECT/battleship_tb.vcd
$date
	Mon Dec 30 16:25:06 2024
$end
$version
	Icarus Verilog
$end
$timescale
	1s
$end
$scope module battleship_tb $end
$var wire 8 ! led [7:0] $end
$var wire 8 " disp3 [7:0] $end
$var wire 8 # disp2 [7:0] $end
$var wire 8 $ disp1 [7:0] $end
$var wire 8 % disp0 [7:0] $end
$var parameter 64 & FP $end
$var parameter 32 ' HP $end
$var reg 2 ( X [1:0] $end
$var reg 2 ) Y [1:0] $end
$var reg 1 * clk $end
$var reg 1 + pAb $end
$var reg 1 , pBb $end
$var reg 1 - rst $end
$var reg 1 . start $end
$scope module ba00 $end
$var wire 2 / X [1:0] $end
$var wire 2 0 Y [1:0] $end
$var wire 1 * clk $end
$var wire 1 + pAb $end
$var wire 1 , pBb $end
$var wire 1 - rst $end
$var wire 1 . start $end
$var parameter 4 1 A_IN $end
$var parameter 4 2 A_SHOOT $end
$var parameter 4 3 A_SINK $end
$var parameter 4 4 A_WIN $end
$var parameter 4 5 B_IN $end
$var parameter 4 6 B_SHOOT $end
$var parameter 4 7 B_SINK $end
$var parameter 4 8 B_WIN $end
$var parameter 4 9 ERROR_A $end
$var parameter 4 : ERROR_B $end
$var parameter 4 ; IDLE $end
$var parameter 4 < SHOW_A $end
$var parameter 4 = SHOW_B $end
$var parameter 4 > SHOW_SCORE $end
$var reg 8 ? disp0 [7:0] $end
$var reg 8 @ disp1 [7:0] $end
$var reg 8 A disp2 [7:0] $end
$var reg 8 B disp3 [7:0] $end
$var reg 4 C index [3:0] $end
$var reg 2 D input_count_A [1:0] $end
$var reg 2 E input_count_B [1:0] $end
$var reg 8 F led [7:0] $end
$var reg 4 G next_state [3:0] $end
$var reg 3 H score_A [2:0] $end
$var reg 3 I score_B [2:0] $end
$var reg 4 J state [3:0] $end
$var reg 16 K timer [15:0] $end
$var reg 16 L timer_winner [15:0] $end
$upscope $end
$upscope $end
$enddefinitions $end
$comment Show the parameter values. $end
$dumpall
b111 >
b100 =
b1 <
b0 ;
b110 :
b11 9
b1101 8
b1100 7
b1011 6
b101 5
b1010 4
b1001 3
b1000 2
b10 1
b101 '
b1100100 &
$end
#0
$dumpvars
b0 L
b0 K
b0 J
b0 I
b0 H
b0 G
b10011001 F
b0 E
b0 D
bx C
b110 B
b111111 A
b111000 @
b1111001 ?
b0 0
b0 /
0.
1-
0,
0+
1*
b0 )
b0 (
b1111001 %
b111000 $
b111111 #
b110 "
b10011001 !
$end
#5
0*
#10
1*
#15
0*
#20
1*
#25
0*
#30
1*
#35
0*
#40
1*
#45
0*
#50
1*
#55
0*
#60
1*
#65
0*
#70
1*
#75
0*
#80
1*
#85
0*
#90
1*
#95
0*
#100
b0 C
1*
0-
#105
0*
#110
1*
#115
0*
#120
1*
#125
0*
#130
1*
#135
0*
#140
1*
#145
0*
#150
1*
#155
0*
#160
1*
#165
0*
#170
1*
#175
0*
#180
1*
#185
0*
#190
1*
#195
0*
#200
b1 G
1*
1.
#205
0*
#210
b0 !
b0 F
b1110111 "
b1110111 B
b0 #
b0 A
b0 $
b0 @
b0 %
b0 ?
b1 J
1*
#215
0*
#220
b1 K
1*
#225
0*
#230
b10 K
1*
#235
0*
#240
b11 K
1*
#245
0*
#250
b100 K
1*
#255
0*
#260
b101 K
1*
#265
0*
#270
b110 K
1*
#275
0*
#280
b111 K
1*
#285
0*
#290
b1000 K
1*
#295
0*
#300
b1001 K
1*
#305
0*
#310
b1010 K
1*
#315
0*
#320
b1011 K
1*
#325
0*
#330
b1100 K
1*
#335
0*
#340
b1101 K
1*
#345
0*
#350
b1110 K
1*
#355
0*
#360
b1111 K
1*
#365
0*
#370
b10000 K
1*
#375
0*
#380
b10001 K
1*
#385
0*
#390
b10010 K
1*
#395
0*
#400
b10011 K
1*
#405
0*
#410
b10100 K
1*
#415
0*
#420
b10101 K
1*
#425
0*
#430
b10110 K
1*
#435
0*
#440
b10111 K
1*
#445
0*
#450
b11000 K
1*
#455
0*
#460
b11001 K
1*
#465
0*
#470
b11010 K
1*
#475
0*
#480
b11011 K
1*
#485
0*
#490
b11100 K
1*
#495
0*
#500
b11101 K
1*
#505
0*
#510
b11110 K
1*
#515
0*
#520
b11111 K
1*
#525
0*
#530
b100000 K
1*
#535
0*
#540
b100001 K
1*
#545
0*
#550
b100010 K
1*
#555
0*
#560
b100011 K
1*
#565
0*
#570
b100100 K
1*
#575
0*
#580
b100101 K
1*
#585
0*
#590
b100110 K
1*
#595
0*
#600
b100111 K
1*
#605
0*
#610
b101000 K
1*
#615
0*
#620
b101001 K
1*
#625
0*
#630
b101010 K
1*
#635
0*
#640
b101011 K
1*
#645
0*
#650
b101100 K
1*
#655
0*
#660
b101101 K
1*
#665
0*
#670
b101110 K
1*
#675
0*
#680
b101111 K
1*
#685
0*
#690
b110000 K
1*
#695
0*
#700
b110001 K
1*
0.
#705
0*
#710
b110010 K
1*
#715
0*
#720
b0 K
b10 G
1*
#725
0*
#730
b0 !
b0 F
b111111 %
b111111 ?
b111111 $
b111111 @
b0 "
b0 B
b1 K
b10 J
1*
#735
0*
#740
b0 K
1*
#745
0*
#750
1*
#755
0*
#760
1*
#765
0*
#770
1*
#775
0*
#780
1*
#785
0*
#790
1*
#795
0*
#800
b1000000 !
b1000000 F
b111111 $
b111111 @
b111111 %
b111111 ?
b1 D
1*
1+
#805
0*
#810
1*
#815
0*
#820
1*
#825
0*
#830
1*
#835
0*
#840
1*
#845
0*
#850
1*
#855
0*
#860
1*
#865
0*
#870
1*
#875
0*
#880
1*
#885
0*
#890
1*
#895
0*
#900
1*
0+
#905
0*
#910
1*
#915
0*
#920
1*
#925
0*
#930
1*
#935
0*
#940
1*
#945
0*
#950
1*
#955
0*
#960
1*
#965
0*
#970
1*
#975
0*
#980
1*
#985
0*
#990
1*
#995
0*
#1000
b100 C
b1000000 !
b1000000 F
b111111 $
b111111 @
b110 %
b110 ?
1*
b1 )
b1 0
1+
#1005
0*
#1010
b10000000 !
b10000000 F
b111111 $
b111111 @
b110 %
b110 ?
b10 D
1*
#1015
0*
#1020
1*
#1025
0*
#1030
1*
#1035
0*
#1040
1*
#1045
0*
#1050
1*
#1055
0*
#1060
1*
#1065
0*
#1070
1*
#1075
0*
#1080
1*
#1085
0*
#1090
1*
#1095
0*
#1100
1*
0+
#1105
0*
#1110
1*
#1115
0*
#1120
1*
#1125
0*
#1130
1*
#1135
0*
#1140
1*
#1145
0*
#1150
1*
#1155
0*
#1160
1*
#1165
0*
#1170
1*
#1175
0*
#1180
1*
#1185
0*
#1190
1*
#1195
0*
#1200
b1 C
b10000000 !
b10000000 F
b110 $
b110 @
b111111 %
b111111 ?
1*
b0 )
b0 0
b1 (
b1 /
1+
#1205
0*
#1210
b11000000 !
b11000000 F
b110 $
b110 @
b111111 %
b111111 ?
b11 D
1*
#1215
0*
#1220
1*
#1225
0*
#1230
1*
#1235
0*
#1240
1*
#1245
0*
#1250
1*
#1255
0*
#1260
1*
#1265
0*
#1270
1*
#1275
0*
#1280
1*
#1285
0*
#1290
1*
#1295
0*
#1300
1*
0+
#1305
0*
#1310
1*
#1315
0*
#1320
1*
#1325
0*
#1330
1*
#1335
0*
#1340
1*
#1345
0*
#1350
1*
#1355
0*
#1360
1*
#1365
0*
#1370
1*
#1375
0*
#1380
1*
#1385
0*
#1390
1*
#1395
0*
#1400
b101 C
b11000000 !
b11000000 F
b110 $
b110 @
b110 %
b110 ?
1*
b1 )
b1 0
1+
#1405
0*
#1410
b100 G
1*
#1415
0*
#1420
b1111111 "
b1111111 B
b0 !
b0 F
b0 $
b0 @
b0 %
b0 ?
b10 G
b100 J
1*
#1425
0*
#1430
b11000000 !
b11000000 F
b110 %
b110 ?
b110 $
b110 @
b0 "
b0 B
b1 K
b10 J
1*
#1435
0*
#1440
b0 K
1*
#1445
0*
#1450
1*
#1455
0*
#1460
1*
#1465
0*
#1470
1*
#1475
0*
#1480
1*
#1485
0*
#1490
1*
#1495
0*
#1500
1*
0+
#1505
0*
#1510
1*
#1515
0*
#1520
1*
#1525
0*
#1530
1*
#1535
0*
#1540
1*
#1545
0*
#1550
1*
#1555
0*
#1560
1*
#1565
0*
#1570
1*
#1575
0*
#1580
1*
#1585
0*
#1590
1*
#1595
0*
#1600
b0 C
b11000000 !
b11000000 F
b111111 $
b111111 @
b111111 %
b111111 ?
1*
b0 )
b0 0
b0 (
b0 /
1,
#1605
0*
#1610
1*
#1615
0*
#1620
1*
#1625
0*
#1630
1*
#1635
0*
#1640
1*
#1645
0*
#1650
1*
#1655
0*
#1660
1*
#1665
0*
#1670
1*
#1675
0*
#1680
1*
#1685
0*
#1690
1*
#1695
0*
#1700
1*
0,
#1705
0*
#1710
1*
#1715
0*
#1720
1*
#1725
0*
#1730
1*
#1735
0*
#1740
1*
#1745
0*
#1750
1*
#1755
0*
#1760
1*
#1765
0*
#1770
1*
#1775
0*
#1780
1*
#1785
0*
#1790
1*
#1795
0*
#1800
b100 C
b11000000 !
b11000000 F
b111111 $
b111111 @
b110 %
b110 ?
1*
b1 )
b1 0
1,
#1805
0*
#1810
1*
#1815
0*
#1820
1*
#1825
0*
#1830
1*
#1835
0*
#1840
1*
#1845
0*
#1850
1*
#1855
0*
#1860
1*
#1865
0*
#1870
1*
#1875
0*
#1880
1*
#1885
0*
#1890
1*
#1895
0*
#1900
1*
0,
#1905
0*
#1910
1*
#1915
0*
#1920
1*
#1925
0*
#1930
1*
#1935
0*
#1940
1*
#1945
0*
#1950
1*
#1955
0*
#1960
1*
#1965
0*
#1970
1*
#1975
0*
#1980
1*
#1985
0*
#1990
1*
#1995
0*
#2000
b1 C
b11000000 !
b11000000 F
b110 $
b110 @
b111111 %
b111111 ?
1*
b0 )
b0 0
b1 (
b1 /
1,
#2005
0*
#2010
1*
#2015
0*
#2020
1*
#2025
0*
#2030
1*
#2035
0*
#2040
1*
#2045
0*
#2050
1*
#2055
0*
#2060
1*
#2065
0*
#2070
1*
#2075
0*
#2080
1*
#2085
0*
#2090
1*
#2095
0*
#2100
1*
0,
#2105
0*
#2110
1*
#2115
0*
#2120
1*
#2125
0*
#2130
1*
#2135
0*
#2140
1*
#2145
0*
#2150
1*
#2155
0*
#2160
1*
#2165
0*
#2170
1*
#2175
0*
#2180
1*
#2185
0*
#2190
1*
#2195
0*
#2200
b101 C
b11000000 !
b11000000 F
b110 $
b110 @
b110 %
b110 ?
1*
b1 )
b1 0
1,
#2205
0*
#2210
1*
#2215
0*
#2220
1*
#2225
0*
#2230
1*
#2235
0*
#2240
1*
#2245
0*
#2250
1*
#2255
0*
#2260
1*
#2265
0*
#2270
1*
#2275
0*
#2280
1*
#2285
0*
#2290
1*
#2295
0*
#2300
1*
0,
#2305
0*
#2310
1*
#2315
0*
#2320
1*
#2325
0*
#2330
1*
#2335
0*
#2340
1*
#2345
0*
#2350
1*
#2355
0*
#2360
1*
#2365
0*
#2370
1*
#2375
0*
#2380
1*
#2385
0*
#2390
1*
#2395
0*
#2400
b0 C
b11000000 !
b11000000 F
b111111 $
b111111 @
b111111 %
b111111 ?
1*
b0 )
b0 0
b0 (
b0 /
1+
#2405
0*
#2410
1*
#2415
0*
#2420
1*
#2425
0*
#2430
1*
#2435
0*
#2440
1*
#2445
0*
#2450
1*
#2455
0*
#2460
1*
#2465
0*
#2470
1*
#2475
0*
#2480
1*
#2485
0*
#2490
1*
#2495
0*
#2500
1*
0+
#2505
0*
#2510
1*
#2515
0*
#2520
1*
#2525
0*
#2530
1*
#2535
0*
#2540
1*
#2545
0*
#2550
1*
#2555
0*
#2560
1*
#2565
0*
#2570
1*
#2575
0*
#2580
1*
#2585
0*
#2590
1*
#2595
0*
#2600
1*
1,
#2605
0*
#2610
1*
#2615
0*
#2620
1*
#2625
0*
#2630
1*
#2635
0*
#2640
1*
#2645
0*
#2650
1*
#2655
0*
#2660
1*
#2665
0*
#2670
1*
#2675
0*
#2680
1*
#2685
0*
#2690
1*
#2695
0*
#2700
1*
0,
#2705
0*
#2710
1*
#2715
0*
#2720
1*
#2725
0*
#2730
1*
#2735
0*
#2740
1*
#2745
0*
#2750
1*
#2755
0*
#2760
1*
#2765
0*
#2770
1*
#2775
0*
#2780
1*
#2785
0*
#2790
1*
#2795
0*
#2800
b100 C
b11000000 !
b11000000 F
b111111 $
b111111 @
b110 %
b110 ?
1*
b1 )
b1 0
1+
#2805
0*
#2810
1*
#2815
0*
#2820
1*
#2825
0*
#2830
1*
#2835
0*
#2840
1*
#2845
0*
#2850
1*
#2855
0*
#2860
1*
#2865
0*
#2870
1*
#2875
0*
#2880
1*
#2885
0*
#2890
1*
#2895
0*
#2900
1*
0+
#2905
0*
#2910
1*
#2915
0*
#2920
1*
#2925
0*
#2930
1*
#2935
0*
#2940
1*
#2945
0*
#2950
1*
#2955
0*
#2960
1*
#2965
0*
#2970
1*
#2975
0*
#2980
1*
#2985
0*
#2990
1*
#2995
0*
#3000
b1 C
b11000000 !
b11000000 F
b110 $
b110 @
b111111 %
b111111 ?
1*
b0 )
b0 0
b1 (
b1 /
1,
#3005
0*
#3010
1*
#3015
0*
#3020
1*
#3025
0*
#3030
1*
#3035
0*
#3040
1*
#3045
0*
#3050
1*
#3055
0*
#3060
1*
#3065
0*
#3070
1*
#3075
0*
#3080
1*
#3085
0*
#3090
1*
#3095
0*
#3100
1*
0,
#3105
0*
#3110
1*
#3115
0*
#3120
1*
#3125
0*
#3130
1*
#3135
0*
#3140
1*
#3145
0*
#3150
1*
#3155
0*
#3160
1*
#3165
0*
#3170
1*
#3175
0*
#3180
1*
#3185
0*
#3190
1*
#3195
0*
#3200
b101 C
b11000000 !
b11000000 F
b110 $
b110 @
b110 %
b110 ?
1*
b1 )
b1 0
1+
#3205
0*
#3210
1*
#3215
0*
#3220
1*
#3225
0*
#3230
1*
#3235
0*
#3240
1*
#3245
0*
#3250
1*
#3255
0*
#3260
1*
#3265
0*
#3270
1*
#3275
0*
#3280
1*
#3285
0*
#3290
1*
#3295
0*
#3300
1*
0+
#3305
0*
#3310
1*
#3315
0*
#3320
1*
#3325
0*
#3330
1*
#3335
0*
#3340
1*
#3345
0*
#3350
1*
#3355
0*
#3360
1*
#3365
0*
#3370
1*
#3375
0*
#3380
1*
#3385
0*
#3390
1*
#3395
0*
#3400
1*
1,
#3405
0*
#3410
1*
#3415
0*
#3420
1*
#3425
0*
#3430
1*
#3435
0*
#3440
1*
#3445
0*
#3450
1*
#3455
0*
#3460
1*
#3465
0*
#3470
1*
#3475
0*
#3480
1*
#3485
0*
#3490
1*
#3495
0*
#3500
1*
0,
#3505
0*
#3510
1*
#3515
0*
#3520
1*
#3525
0*
#3530
1*
#3535
0*
#3540
1*
#3545
0*
#3550
1*
#3555
0*
#3560
1*
#3565
0*
#3570
1*
#3575
0*
#3580
1*
#3585
0*
#3590
1*
#3595
0*
#3600
1*
1+
#3605
0*
#3610
1*
#3615
0*
#3620
1*
#3625
0*
#3630
1*
#3635
0*
#3640
1*
#3645
0*
#3650
1*
#3655
0*
#3660
1*
#3665
0*
#3670
1*
#3675
0*
#3680
1*
#3685
0*
#3690
1*
#3695
0*
#3700
1*
0+
#3705
0*
#3710
1*
#3715
0*
#3720
1*
#3725
0*
#3730
1*
#3735
0*
#3740
1*
#3745
0*
#3750
1*
#3755
0*
#3760
1*
#3765
0*
#3770
1*
#3775
0*
#3780
1*
#3785
0*
#3790
1*
#3795
0*
