LAB1/LAB2_cs303.v
/*
 * Generated by Digital. Don't modify this file!
 * Any changes will be lost if this file is regenerated.
 */

module LAB2_cs303 (
  input X1,
  input X0,
  input Y1,
  input Y0,
  output A1,
  output A0
);
  assign A0 = (X0 & Y0);
  assign A1 = (((~ X1 & X0 & Y1) | (X1 & ~ X0 & Y0)) | ((X0 & ~ Y0 & Y1) | (X1 & Y0 & ~ Y1)));
endmodule

LAB1/LAB2_cs303_tb.v
module LAB2_cs303_tb();

reg X1,X0,Y1,Y0;  // Inputs are registers.
wire A1,A0;   // Outputs are wires.

LAB2_cs303 dut(X1,X0,Y1,Y0,A1,A0); // Our design-under-test.

initial begin
    //  * Our waveform is saved under this file.
    
    $dumpfile("LAB2_cs303.vcd"); 
    
    // * Get the variables from the module.

    $dumpvars(0,LAB2_cs303_tb);

    $display("Simulation started.");
    X1 = 0;  // Set all inputs to zero.
    X0 = 0;
    Y1 = 0;
    Y0 = 0;
    #10;     // Wait 10 time units.
    X1 = 0;  // Set all inputs to zero.
    X0 = 0;
    Y1 = 0;
    Y0 = 1;
    #10; 
    X1 = 0;  // Set all inputs to zero.
    X0 = 0;
    Y1 = 1;
    Y0 = 0;
    #10;
    X1 = 0;  // Set all inputs to zero.
    X0 = 0;
    Y1 = 1;
    Y0 = 1;
    #10;
    X1 = 0;  // Set all inputs to zero.
    X0 = 1;
    Y1 = 0;
    Y0 = 0;
    #10;
    X1 = 0;  // Set all inputs to zero.
    X0 = 1;
    Y1 = 0;
    Y0 = 1;
    #10;
    X1 = 0;  // Set all inputs to zero.
    X0 = 1;
    Y1 = 1;
    Y0 = 0;
    #10;
    X1 = 0;  // Set all inputs to zero.
    X0 = 1;
    Y1 = 1;
    Y0 = 1;
    #10;
    X1 = 1;  // Set all inputs to zero.
    X0 = 0;
    Y1 = 0;
    Y0 = 0;
    #10;
    X1 = 1;  // Set all inputs to zero.
    X0 = 0;
    Y1 = 0;
    Y0 = 1;
    #10;
    X1 = 1;  // Set all inputs to zero.
    X0 = 0;
    Y1 = 1;
    Y0 = 0;
    #10;
    X1 = 1;  // Set all inputs to zero.
    X0 = 0;
    Y1 = 1;
    Y0 = 1;
    #10;
    X1 = 1;  // Set all inputs to zero.
    X0 = 1;
    Y1 = 0;
    Y0 = 0;
    #10;
    X1 = 1;  // Set all inputs to zero.
    X0 = 1;
    Y1 = 0;
    Y0 = 1;
    #10;
    X1 = 1;  // Set all inputs to zero.
    X0 = 1;
    Y1 = 1;
    Y0 = 0;
    #10;
    X1 = 1;  // Set all inputs to zero.
    X0 = 1;
    Y1 = 1;
    Y0 = 1;
    #10;
    $display("Simulation finished.");
    $finish(); // Finish simulation.
end

endmodule

LAB1/LAB2_cs303.vcd
$date
	Thu Nov 14 12:17:57 2024
$end
$version
	Icarus Verilog
$end
$timescale
	1s
$end
$scope module LAB2_cs303_tb $end
$var wire 1 ! A1 $end
$var wire 1 " A0 $end
$var reg 1 # X0 $end
$var reg 1 $ X1 $end
$var reg 1 % Y0 $end
$var reg 1 & Y1 $end
$scope module dut $end
$var wire 1 " A0 $end
$var wire 1 ! A1 $end
$var wire 1 # X0 $end
$var wire 1 $ X1 $end
$var wire 1 % Y0 $end
$var wire 1 & Y1 $end
$upscope $end
$upscope $end
$enddefinitions $end
$comment Show the parameter values. $end
$dumpall
$end
#0
$dumpvars
0&
0%
0$
0#
0"
0!
$end
#10
1%
#20
0%
1&
#30
1%
#40
0%
0&
1#
#50
1"
1%
#60
1!
0"
0%
1&
#70
1"
1%
#80
0!
0"
0%
0&
0#
1$
#90
1!
1%
#100
0!
0%
1&
#110
1!
1%
#120
0!
0%
0&
1#
#130
1!
1"
1%
#140
1!
0"
0%
1&
#150
0!
1"
1%
