LAB3/matrixops.v
module matrixops (
  input            clk,
  input            rst,
  input            enter,
  input      [1:0] X,
  input      [1:0] Y,
  output reg       Z
);

  parameter S0 = 2'b00; //Default State
  parameter S1 = 2'b01; //Input Waiting 
  parameter S2 = 2'b10; //Input Process
  parameter S3 = 2'b11; //Output Process
  //Taken from Verilog_3.pptx

  reg [1:0] cState; //current state of FSM 
  reg matrix [3:0][3:0]; //4x4 matrix implementation 
  reg [2:0] input_count; //from log2(5)>2 our needed space is 3
  integer i, j; //will use them for reset the matrix
  reg other_Z;

  always @(posedge clk or posedge rst) 
  begin
    if (rst) //if reset is high
    begin
      for (i = 0; i < 4; i = i + 1) begin
        for (j = 0; j < 4; j = j + 1) begin
          matrix[i][j] <= 0; //Setting all matrix cells into 0 here
        end
      end
      input_count <= 0; //reset input count 
      Z <= 0; 
      other_Z <= 0; 
      cState <= S0; //setting current state to default 
    end //reset all the states 
    else 
    begin
      if (cState == S0) 
      begin
        if (enter) 
          cState <= S1; //transition to S1
      end 
      else if (cState == S1) 
      begin
        cState <= S2;
      end  //going into s2
      else if (cState == S2) 
      begin
        if (input_count == 4 && enter) 
        begin
          matrix[Y][X] <= 1;
          input_count <= input_count + 1;
          cState <= S3; 
        end //input processing state if(user entered 5 inputs set current state into next state ( state 3 output query state)).
        else if (enter) 
        begin
          matrix[Y][X] <= 1; 
          input_count <= input_count + 1; //while count is not 5 add 1 into the corresponding cell and increase input count.
        end
      end 
      else if (cState == S3) 
      begin
        if (rst) 
        begin
          Z <= 0;
          other_Z <= 0;
        end //if reset is high set both Z's to 0 
        else if (enter) 
        begin
          other_Z <= matrix[Y][X]; //while user enters enter output the corresponding cells 
        end
        Z <= other_Z;
      end
    end
  end
endmodule

LAB3/matrixops_tb-2.v
module matrixops_tb ();

  reg        clk;
  reg        rst;
  reg        enter;
  reg  [1:0] X;
  reg  [1:0] Y;
  wire       Z;

  matrixops dut (
    .clk  (clk),
    .rst  (rst),
    .enter(enter),
    .X    (X),
    .Y    (Y),
    .Z    (Z)
  );

  parameter HP = 5;
  parameter FP = (2 * HP);

  always #HP clk = ~clk;

  initial begin
    $dumpfile("matrixops_tb.vcd");
    $dumpvars(0, matrixops_tb);

    $display("Simulation started.");

    //I tried TestCase2 here lately

    clk = 1;
    rst = 1;
    X = 0;
    Y = 0;
    enter = 0;
    #(FP - 1);

    rst = 0;
    X = 0;
    Y = 0;
    enter = 1;
    #FP;

    rst = 0;
    X = 0;
    Y = 0;
    enter = 0;
    #FP;

    rst = 0;
    X = 0;
    Y = 1;
    enter = 1;
    #FP;

    rst = 0;
    X = 2;
    Y = 3;
    enter = 1;
    #FP;

    rst = 0;
    X = 3;
    Y = 2;
    enter = 1;
    #FP;

    rst = 0;
    X = 1;
    Y = 0;
    enter = 1;
    #FP;

    rst = 0;
    X = 0;
    Y =0;
    enter = 1;
    #FP;

    rst = 0;
    X = 1;
    Y = 1;
    enter = 1;
    #FP;

    rst = 0;
    X = 1;
    Y = 1;
    enter = 0;
    #FP;


    rst = 0;
    X = 1;
    Y = 1;
    enter = 0;
    #FP;

    rst = 0;
    X = 0;
    Y = 0;
    enter = 0;
    #FP;

    rst = 0;
    X = 0;
    Y = 0;
    enter = 1;
    #FP;

    rst = 0;
    X = 2;
    Y = 0;
    enter = 1;
    #FP;

    rst = 0;
    X = 2;
    Y = 0;
    enter = 0;
    #FP;

    $display("Simulation finished.");
    $finish();
  end

endmodule

LAB3/matrixops_tb.vcd
$date
	Mon Dec  9 10:48:25 2024
$end
$version
	Icarus Verilog
$end
$timescale
	1s
$end
$scope module matrixops_tb $end
$var wire 1 ! Z $end
$var parameter 64 " FP $end
$var parameter 32 # HP $end
$var reg 2 $ X [1:0] $end
$var reg 2 % Y [1:0] $end
$var reg 1 & clk $end
$var reg 1 ' enter $end
$var reg 1 ( rst $end
$scope module dut $end
$var wire 2 ) X [1:0] $end
$var wire 2 * Y [1:0] $end
$var wire 1 & clk $end
$var wire 1 ' enter $end
$var wire 1 ( rst $end
$var parameter 2 + S0 $end
$var parameter 2 , S1 $end
$var parameter 2 - S2 $end
$var parameter 2 . S3 $end
$var reg 1 ! Z $end
$var reg 2 / cState [1:0] $end
$var reg 3 0 input_count [2:0] $end
$var reg 1 1 other_Z $end
$var integer 32 2 i [31:0] $end
$var integer 32 3 j [31:0] $end
$upscope $end
$upscope $end
$enddefinitions $end
$comment Show the parameter values. $end
$dumpall
b11 .
b10 -
b1 ,
b0 +
b101 #
b1010 "
$end
#0
$dumpvars
b100 3
b100 2
01
b0 0
b0 /
b0 *
b0 )
1(
0'
1&
b0 %
b0 $
0!
$end
#5
0&
#9
1'
0(
#10
b1 /
1&
#15
0&
#19
0'
#20
b10 /
1&
#25
0&
#29
1'
b1 %
b1 *
#30
b1 0
1&
#35
0&
#39
b11 %
b11 *
b10 $
b10 )
#40
b10 0
1&
#45
0&
#49
b10 %
b10 *
b11 $
b11 )
#50
b11 0
1&
#55
0&
#59
b0 %
b0 *
b1 $
b1 )
#60
b100 0
1&
#65
0&
#69
b0 $
b0 )
#70
b11 /
b101 0
1&
#75
0&
#79
b1 %
b1 *
b1 $
b1 )
#80
1&
#85
0&
#89
0'
#90
1&
#95
0&
#100
1&
#105
0&
#109
b0 %
b0 *
b0 $
b0 )
#110
1&
#115
0&
#119
1'
#120
11
1&
#125
0&
#129
b10 $
b10 )
#130
1!
01
1&
#135
0&
#139
0'
#140
0!
1&
